odoo/addons/shopfloor_checkout_package_measurement_mobile/README.rst
odoo/addons/shopfloor_checkout_package_measurement_mobile/__init__.py
odoo/addons/shopfloor_checkout_package_measurement_mobile/__manifest__.py
odoo/addons/shopfloor_checkout_package_measurement_mobile/i18n/shopfloor_checkout_package_measurement_mobile.pot
odoo/addons/shopfloor_checkout_package_measurement_mobile/readme/CONTRIBUTORS.rst
odoo/addons/shopfloor_checkout_package_measurement_mobile/readme/DESCRIPTION.rst
odoo/addons/shopfloor_checkout_package_measurement_mobile/static/description/icon.png
odoo/addons/shopfloor_checkout_package_measurement_mobile/static/description/index.html
odoo/addons/shopfloor_checkout_package_measurement_mobile/static/src/scenario/checkout_package_measurement.js
odoo/addons/shopfloor_checkout_package_measurement_mobile/templates/assets.xml
odoo14_addon_shopfloor_checkout_package_measurement_mobile-14.0.1.0.3.dist-info/METADATA
odoo14_addon_shopfloor_checkout_package_measurement_mobile-14.0.1.0.3.dist-info/WHEEL
odoo14_addon_shopfloor_checkout_package_measurement_mobile-14.0.1.0.3.dist-info/top_level.txt
odoo14_addon_shopfloor_checkout_package_measurement_mobile-14.0.1.0.3.dist-info/RECORD
